showsys/__init__.py
showsys/cli.py
showsys/showsys.py
ShowSys-1.0.1.dist-info/LICENSE
ShowSys-1.0.1.dist-info/METADATA
ShowSys-1.0.1.dist-info/WHEEL
ShowSys-1.0.1.dist-info/entry_points.txt
ShowSys-1.0.1.dist-info/top_level.txt
ShowSys-1.0.1.dist-info/RECORD
