Metadata-Version: 2.1
Name: ShowSys
Version: 1.0.1
Summary: A simple package to get system spec information
Home-page: https://github.com/natlee/show-system-info
Author: Nat Lee
Author-email: natlee.work@gmail.com
Project-URL: Documentation, https://github.com/natlee/show-system-info
Project-URL: Bug Reports, https://github.com/natlee/show-system-info/issues
Project-URL: Source Code, https://github.com/natlee/show-system-info
Keywords: system,information,spec,hardware,software,os,platform,cpu,memory,disk,network,cli,command,line,interface,tool,utility
Classifier: Development Status :: 5 - Production/Stable
Classifier: Intended Audience :: Developers
Classifier: Topic :: Software Development :: Build Tools
Classifier: Programming Language :: Python :: 3
Classifier: Programming Language :: Python :: 3.7
Classifier: Programming Language :: Python :: 3.8
Classifier: Programming Language :: Python :: 3.9
Classifier: Programming Language :: Python :: 3.10
Classifier: Programming Language :: Python :: 3.11
Classifier: Programming Language :: Python :: 3 :: Only
Classifier: License :: OSI Approved :: MIT License
Classifier: Operating System :: OS Independent
Requires-Python: >=3.7
License-File: LICENSE
Requires-Dist: psutil
Requires-Dist: py-cpuinfo
Provides-Extra: dev
Requires-Dist: check-manifest ; extra == 'dev'
